folderize/__init__.py
folderize/core.py
folderize-0.1.0.dist-info/licenses/LICENSE
folderize-0.1.0.dist-info/METADATA
folderize-0.1.0.dist-info/WHEEL
folderize-0.1.0.dist-info/entry_points.txt
folderize-0.1.0.dist-info/top_level.txt
folderize-0.1.0.dist-info/RECORD
