Metadata-Version: 2.4
Name: folderize
Version: 0.1.0
Summary: Automate repetitive folder and file creation
Author-email: Sanjay RB <sanjaybabu618@gmail.com>
License: MIT
Requires-Python: >=3.8
License-File: LICENSE
Dynamic: license-file
